setup.py
src/giraffe/__init__.py
src/giraffe/features.py
src/giraffe/gb.py
src/giraffe/models.py
src/giraffe/orfs.py
src/giraffe/tags.py
src/giraffe/tests.py
src/giraffe/urls.py
src/giraffe/views.py
src/giraffe.egg-info/PKG-INFO
src/giraffe.egg-info/SOURCES.txt
src/giraffe.egg-info/dependency_links.txt
src/giraffe.egg-info/not-zip-safe
src/giraffe.egg-info/requires.txt
src/giraffe.egg-info/top_level.txt
src/hippo/__init__.py
src/hippo/admin.py
src/hippo/models.py
src/hippo/management/__init__.py
src/hippo/management/commands/__init__.py
src/hippo/management/commands/build_blastdb.py
src/hippo/migrations/0001_initial.py
src/hippo/migrations/0002_auto__del_field_feature_cut_after.py
src/hippo/migrations/0003_auto__del_field_feature_hash__del_unique_feature_hash_name.py
src/hippo/migrations/0004_auto__add_field_feature_dna_or_protein.py
src/hippo/migrations/__init__.py