Metadata-Version: 1.1
Name: giraffe
Version: 2.0
Summary: Sequence BLAST, feature detection, and visualization
Home-page: UNKNOWN
Author: Benjie Chen
Author-email: benjie@alum.mit.edu
License: UNKNOWN
Platform: UNKNOWN
Classifier: Operating System :: OS Independent
Classifier: Programming Language :: Python
Classifier: Topic :: Utilities
